hcai_dataset_utils/__init__.py
hcai_dataset_utils/bridge_pytorch.py
hcai_dataset_utils/bridge_tf.py
hcai_dataset_utils/dataset_indexed.py
hcai_dataset_utils/import_validator.py
hcai_dataset_utils/pytorch_dataset_wrapper.py
hcai_dataset_utils/statistics.py
hcai_datasets/__init__.py
hcai_datasets/hcai_affectnet/__init__.py
hcai_datasets/hcai_affectnet/example.py
hcai_datasets/hcai_affectnet/hcai_affectnet.py
hcai_datasets/hcai_affectnet/hcai_affectnet_iterable.py
hcai_datasets/hcai_affectnet/Ignore_Lists/affect_net_ignore_list_duplicates.json
hcai_datasets/hcai_affectnet/Ignore_Lists/affect_net_ignore_list_wrong_format.json
hcai_datasets/hcai_audioset/__init__.py
hcai_datasets/hcai_audioset/example.py
hcai_datasets/hcai_audioset/hcai_audioset.py
hcai_datasets/hcai_ckplus/__init__.py
hcai_datasets/hcai_ckplus/example.py
hcai_datasets/hcai_ckplus/hcai_ckplus.py
hcai_datasets/hcai_ckplus/hcai_ckplus_iterable.py
hcai_datasets/hcai_faces/__init__.py
hcai_datasets/hcai_faces/example.py
hcai_datasets/hcai_faces/hcai_faces.py
hcai_datasets/hcai_faces/hcai_faces_iterable.py
hcai_datasets/hcai_is2021_ess/__init__.py
hcai_datasets/hcai_is2021_ess/example.py
hcai_datasets/hcai_is2021_ess/hcai_is2021_ess.py
hcai_datasets/hcai_librispeech/__init__.py
hcai_datasets/hcai_librispeech/example.py
hcai_datasets/hcai_librispeech/hcai_librispeech.py
hcai_datasets/hcai_librispeech/preprocessing.py
hcai_datasets/hcai_nova_dynamic/__init__.py
hcai_datasets/hcai_nova_dynamic/hcai_nova_dynamic_iterable.py
hcai_datasets/hcai_nova_dynamic/nova_db_handler.py
hcai_datasets/hcai_nova_dynamic/utils/__init__.py
hcai_datasets/hcai_nova_dynamic/utils/nova_anno_utils.py
hcai_datasets/hcai_nova_dynamic/utils/nova_data_utils.py
hcai_datasets/hcai_nova_dynamic/utils/nova_string_utils.py
hcai_datasets-0.1.14.dist-info/METADATA
hcai_datasets-0.1.14.dist-info/WHEEL
hcai_datasets-0.1.14.dist-info/top_level.txt
hcai_datasets-0.1.14.dist-info/RECORD
